cloopui/__init__.py
cloopui/template.html
cloopui-0.3.dist-info/METADATA
cloopui-0.3.dist-info/WHEEL
cloopui-0.3.dist-info/top_level.txt
cloopui-0.3.dist-info/RECORD
